hil/can/gc/CHUSBDLL64.dll
hil/can/gc/ECanVci.py
hil/can/gc/ECanVci64.dll
hil/can/gc/__init__.py
hil/can/gc/bus.py
python_can_gc-0.0.3.dist-info/LICENSE
python_can_gc-0.0.3.dist-info/METADATA
python_can_gc-0.0.3.dist-info/WHEEL
python_can_gc-0.0.3.dist-info/entry_points.txt
python_can_gc-0.0.3.dist-info/top_level.txt
python_can_gc-0.0.3.dist-info/RECORD
